learning_hypermodern/__init__.py
learning_hypermodern/console.py
learning_hypermodern/wikipedia.py
learning_hypermodern-0.1.3.dist-info/entry_points.txt
learning_hypermodern-0.1.3.dist-info/LICENSE
learning_hypermodern-0.1.3.dist-info/WHEEL
learning_hypermodern-0.1.3.dist-info/METADATA
learning_hypermodern-0.1.3.dist-info/RECORD
